ciscodnacnetbox/.DS_Store
ciscodnacnetbox/__init__.py
ciscodnacnetbox/admin.py
ciscodnacnetbox/forms.py
ciscodnacnetbox/metadata.py
ciscodnacnetbox/models.py
ciscodnacnetbox/navigation.py
ciscodnacnetbox/tables.py
ciscodnacnetbox/urls.py
ciscodnacnetbox/views.py
ciscodnacnetbox/__pycache__/__init__.cpython-39.pyc
ciscodnacnetbox/ciscodnac/__init__.py
ciscodnacnetbox/ciscodnac/data.py
ciscodnacnetbox/ciscodnac/netbox.py
ciscodnacnetbox/ciscodnac/utilities.py
ciscodnacnetbox/ciscodnac/__pycache__/__init__.cpython-38.pyc
ciscodnacnetbox/ciscodnac/__pycache__/data.cpython-38.pyc
ciscodnacnetbox/ciscodnac/__pycache__/netbox.cpython-38.pyc
ciscodnacnetbox/ciscodnac/__pycache__/utilities.cpython-38.pyc
ciscodnacnetbox/migrations/0001_initial.py
ciscodnacnetbox/migrations/__init__.py
ciscodnacnetbox/migrations/__pycache__/0001_initial.cpython-38.pyc
ciscodnacnetbox/migrations/__pycache__/__init__.cpython-38.pyc
ciscodnacnetbox/templates/.DS_Store
ciscodnacnetbox/templates/ciscodnacnetbox/devices.html
ciscodnacnetbox/templates/ciscodnacnetbox/loading_job.html
ciscodnacnetbox/templates/ciscodnacnetbox/purge_tenant.html
ciscodnacnetbox/templates/ciscodnacnetbox/settings.html
ciscodnacnetbox/templates/ciscodnacnetbox/settings_edit.html
ciscodnacnetbox/templates/ciscodnacnetbox/sites.html
ciscodnacnetbox/templates/ciscodnacnetbox/status.html
ciscodnacnetbox/templates/ciscodnacnetbox/sync_devices.html
ciscodnacnetbox/templates/ciscodnacnetbox/sync_full.html
ciscodnacnetbox/templates/ciscodnacnetbox/sync_full_failed.html
ciscodnacnetbox/templates/ciscodnacnetbox/sync_sites.html
ciscodnacnetbox/templates/ciscodnacnetbox/tables.html
ciscodnacnetbox-3.5.0.dist-info/LICENSE
ciscodnacnetbox-3.5.0.dist-info/METADATA
ciscodnacnetbox-3.5.0.dist-info/WHEEL
ciscodnacnetbox-3.5.0.dist-info/top_level.txt
ciscodnacnetbox-3.5.0.dist-info/RECORD
