Metadata-Version: 2.1
Name: ciscodnacnetbox
Version: 3.5.0
Summary: Cisco DNA Center Integration with NetBox
Home-page: https://github.com/robertcsapo/ciscodnacnetbox
Author: Robert Csapo
Author-email: rcsapo@cisco.com
License: CISCO SAMPLE CODE LICENSE
Requires-Python: >=3.3
License-File: LICENSE
Requires-Dist: dnacentersdk (==2.6.9)
